flame8_test/__init__.py
flame8_test-0.1.1.dist-info/entry_points.txt
flame8_test-0.1.1.dist-info/WHEEL
flame8_test-0.1.1.dist-info/METADATA
flame8_test-0.1.1.dist-info/RECORD
