Metadata-Version: 2.1
Name: flame8-test
Version: 0.1.1
Summary: Lints Python code blocks in Markdown files using flake8
Home-page: https://github.com/johnfraney/flake8-markdown
License: MIT
Keywords: flake8,markdown,lint
Author: Abdel Jaidi
Author-email: flake8@gmail.com
Requires-Python: >=3.6,<4.0
Classifier: Environment :: Console
Classifier: Framework :: Flake8
Classifier: License :: OSI Approved :: MIT License
Classifier: Operating System :: OS Independent
Classifier: Programming Language :: Python :: 3
Classifier: Programming Language :: Python :: 3.10
Classifier: Programming Language :: Python :: 3.6
Classifier: Programming Language :: Python :: 3.7
Classifier: Programming Language :: Python :: 3.8
Classifier: Programming Language :: Python :: 3.9
Classifier: Topic :: Software Development :: Documentation
Classifier: Topic :: Software Development :: Libraries :: Python Modules
Classifier: Topic :: Software Development :: Quality Assurance
Requires-Dist: flake8 (>=3.7,<4.0)
Project-URL: Repository, https://github.com/johnfraney/flake8-markdown
